pmark.cp37-win_amd64.pyd
pmarker-0.2.1.dist-info/METADATA
pmarker-0.2.1.dist-info/WHEEL
pmarker-0.2.1.dist-info/top_level.txt
pmarker-0.2.1.dist-info/RECORD
