Metadata-Version: 2.1
Name: pmarker
Version: 0.2.1
Summary: Python package for marking PDF files
Author: Schlarbaum Langlois
Author-email: aldabadoreenfc5272@gmail.com
License: GPL
Platform: nt
Requires-Python: ==3.7.*
Requires-Dist: pymupdf
Requires-Dist: beautifulsoup4
